geek_cafe_saas_sdk/__init__.py
geek_cafe_saas_sdk/core/__init__.py
geek_cafe_saas_sdk/core/anonymous_context.py
geek_cafe_saas_sdk/core/audit_mixin.py
geek_cafe_saas_sdk/core/chaos_config.py
geek_cafe_saas_sdk/core/connection_pool.py
geek_cafe_saas_sdk/core/error_codes.py
geek_cafe_saas_sdk/core/field_transformer.py
geek_cafe_saas_sdk/core/model_field_validator.py
geek_cafe_saas_sdk/core/request_context.py
geek_cafe_saas_sdk/core/retry_config.py
geek_cafe_saas_sdk/core/role_mapper.py
geek_cafe_saas_sdk/core/service_errors.py
geek_cafe_saas_sdk/core/service_factory.py
geek_cafe_saas_sdk/core/service_interfaces.py
geek_cafe_saas_sdk/core/service_result.py
geek_cafe_saas_sdk/core/services_container.py
geek_cafe_saas_sdk/core/system_request_context.py
geek_cafe_saas_sdk/core/tenant_settings.py
geek_cafe_saas_sdk/core/validation_result.py
geek_cafe_saas_sdk/core/access/__init__.py
geek_cafe_saas_sdk/core/access/access_checker.py
geek_cafe_saas_sdk/core/access/resource_share_checker.py
geek_cafe_saas_sdk/core/audit/__init__.py
geek_cafe_saas_sdk/core/audit/audit_event.py
geek_cafe_saas_sdk/core/audit/audit_log_model.py
geek_cafe_saas_sdk/core/audit/audit_logger_factory.py
geek_cafe_saas_sdk/core/audit/audit_logger_protocol.py
geek_cafe_saas_sdk/core/audit/composite_audit_logger.py
geek_cafe_saas_sdk/core/audit/dynamodb_audit_logger.py
geek_cafe_saas_sdk/core/audit/noop_audit_logger.py
geek_cafe_saas_sdk/core/audit/s3_audit_logger.py
geek_cafe_saas_sdk/core/coordination/__init__.py
geek_cafe_saas_sdk/core/coordination/batch_coordination_strategy.py
geek_cafe_saas_sdk/core/coordination/coordination_strategy.py
geek_cafe_saas_sdk/core/coordination/counter_coordination_strategy.py
geek_cafe_saas_sdk/core/decorators/__init__.py
geek_cafe_saas_sdk/core/decorators/retry.py
geek_cafe_saas_sdk/core/handlers/resource_meta/app.py
geek_cafe_saas_sdk/core/models/__init__.py
geek_cafe_saas_sdk/core/models/base_async_event_model.py
geek_cafe_saas_sdk/core/models/base_model.py
geek_cafe_saas_sdk-0.110.1.dist-info/METADATA
geek_cafe_saas_sdk-0.110.1.dist-info/WHEEL
geek_cafe_saas_sdk-0.110.1.dist-info/licenses/LICENSE
geek_cafe_saas_sdk-0.110.1.dist-info/RECORD
